LICENSE
README.md
setup.py
cv3/__init__.py
cv3/_draw.py
cv3/_transform.py
cv3/_utils.py
cv3/color_spaces.py
cv3/create.py
cv3/draw.py
cv3/io.py
cv3/opt.py
cv3/processing.py
cv3/transform.py
cv3/utils.py
cv3/video.py
cv3.egg-info/PKG-INFO
cv3.egg-info/SOURCES.txt
cv3.egg-info/dependency_links.txt
cv3.egg-info/requires.txt
cv3.egg-info/top_level.txt
tests/test_draw.py
tests/test_io.py
tests/test_other.py
tests/test_processing.py
tests/test_transform.py
tests/test_video.py
tests/test_video_webcam.py
tests/test_window.py