Metadata-Version: 2.4
Name: cv3
Version: 1.3.1
Summary: Pythonic cv2
Home-page: https://github.com/gorodion/cv3
Author: gorodion
Author-email: domonion@list.ru
License: Apache 2.0
Project-URL: Documentation, https://cv3.readthedocs.io/en/latest/
Project-URL: Source, https://github.com/gorodion/cv3
License-File: LICENSE
Requires-Dist: numpy>=1.19.5
Requires-Dist: opencv-python>=4.2.0.34
Dynamic: author
Dynamic: author-email
Dynamic: home-page
Dynamic: license
Dynamic: license-file
Dynamic: project-url
Dynamic: requires-dist
Dynamic: summary
